
{
  "data": {
      "article": {
          "artcContents": "<p style=\"text-align: center;\"><span style=\"font-size: 13.3333px; text-align: start;\">안녕하세요, kt wiz 야구단입니다.</span></p><p style=\"text-align: center;\"><span style=\"font-size: 13.3333px; text-align: start;\">&nbsp;kt sports에서 채용전환형 인턴사원을 모집합니다.&nbsp;</span></p><p style=\"text-align: center;\"><span style=\"font-size: 13.3333px; text-align: start;\">자세한 내용은 공지 이미지를 확인해주세요.</span></p><p style=\"text-align: center;\"><span style=\"font-size: 13.3333px; text-align: start;\">&nbsp;*지원은 KT그룹 채용 홈페이지에서만 가능합니다.&nbsp;</span></p><p style=\"text-align: center;\"><span style=\"font-size: 13.3333px; text-align: start;\"><br></span></p><p style=\"text-align: center;\"><span style=\"font-size: 13.3333px; text-align: start;\">스포츠엔터테인먼트에 관심 있는 인재를 기다립니다!&nbsp;</span><span style=\"font-size: 13.3333px; text-align: start;\"><br></span></p><p style=\"text-align: center;\"><span style=\"font-size: 14pt;\">[</span><a href=\"https://kt.recruiter.co.kr/app/jobnotice/view?systemKindCode=MRS2&amp;jobnoticeSn=183846\" hyb-browser=\"\" style=\"font-size: 13.3333px; text-align: start;\"><b><span style=\"font-size: 14pt;\">지원 사이트 바로가기</span></b></a><span style=\"font-size: 14pt;\">]</span><br></p><p style=\"text-align: center;\"><img src=\"https://wizzap.ktwiz.co.kr/files/article/2024/06/12/20240612140339.091-74b5cbbdb0d9.jpg\" class=\"txc-image\" style=\"clear:none;float:none;\"></p><p style=\"text-align: center;\"><br><br></p>",
          "artcNextSeq": 187595,
          "artcPrevSeq": 187735,
          "artcSeq": 187627,
          "artcTitle": "[채용] 2024 kt sports 채용전환형 인턴 모집(국제업무/마케팅/디자인)",
          "boardCatSeq": 0,
          "boardCode": "001",
          "delYn": "N",
          "endDttm": 253402225200000,
          "imgFilePath": "https://wizzap.ktwiz.co.kr/files/article/2024/06/12/20240612140411.e94-ced6f65e8892.jpg",
          "maxArticlePerPage": 0,
          "regDttm": 1718118000000,
          "regr": "rlawjdgus117",
          "startDttm": 1718118000000,
          "updDttm": 1718169203000,
          "updr": "rlawjdgus117",
          "useYn": "Y",
          "viewCnt": 437
      }
  }
}